splitfdm/__init__.py
splitfdm/bc.py
splitfdm/boundary.py
splitfdm/cell.py
splitfdm/constants.py
splitfdm/derivatives.py
splitfdm/domain.py
splitfdm/error.py
splitfdm/initialize.py
splitfdm/model.py
splitfdm/refine.py
splitfdm/simulation.py
splitfdm/system.py
splitfdm/visualize.py
splitfdm/equations/__init__.py
splitfdm/equations/transport.py
SplitFDM-0.1.3.dist-info/LICENSE
SplitFDM-0.1.3.dist-info/METADATA
SplitFDM-0.1.3.dist-info/WHEEL
SplitFDM-0.1.3.dist-info/top_level.txt
SplitFDM-0.1.3.dist-info/RECORD
