Metadata-Version: 2.1
Name: SplitFDM
Version: 0.1.3
Summary: 1D Finite-Difference Split Newton Solver
Home-page: https://github.com/gpavanb1/SplitFDM
Author: gpavanb1
Author-email: gpavanb@gmail.com
License: MIT
Project-URL: Bug Reports, https://github.com/gpavanb1/SplitFDM/issues
Project-URL: Source, https://github.com/gpavanb1/SplitFDM/
Keywords: amr newton python finite-difference armijo optimization pseudotransient splitting
Platform: UNKNOWN
Classifier: Topic :: Scientific/Engineering :: Mathematics
Classifier: License :: OSI Approved :: MIT License
Classifier: Programming Language :: Python :: 3
Classifier: Programming Language :: Python :: 3 :: Only
Requires-Dist: numpy
Requires-Dist: numdifftools
Requires-Dist: matplotlib
Requires-Dist: splitnewton
